fireREST/__init__.py
fireREST/defaults.py
fireREST/exceptions.py
fireREST/mapping.py
fireREST/utils.py
fireREST/version.py
fireREST/fmc/__init__.py
fireREST/fmc/assignment/__init__.py
fireREST/fmc/assignment/policyassignment/__init__.py
fireREST/fmc/audit/__init__.py
fireREST/fmc/audit/auditrecord/__init__.py
fireREST/fmc/chassis/__init__.py
fireREST/fmc/chassis/interface/__init__.py
fireREST/fmc/chassis/networkmodule/__init__.py
fireREST/fmc/chassis/operational/__init__.py
fireREST/fmc/deployment/__init__.py
fireREST/fmc/deployment/deployabledevice/__init__.py
fireREST/fmc/deployment/deployabledevice/deployment/__init__.py
fireREST/fmc/deployment/deployabledevice/pendingchanges/__init__.py
fireREST/fmc/deployment/deploymentrequest/__init__.py
fireREST/fmc/deployment/jobhistory/__init__.py
fireREST/fmc/deployment/rollbackrequest/__init__.py
fireREST/fmc/device/__init__.py
fireREST/fmc/device/devicerecord/__init__.py
fireREST/fmc/device/devicerecord/bridgegroupinterface/__init__.py
fireREST/fmc/device/devicerecord/etherchannelinterface/__init__.py
fireREST/fmc/device/devicerecord/fpinterfacestatistics/__init__.py
fireREST/fmc/device/devicerecord/fplogicalinterface/__init__.py
fireREST/fmc/device/devicerecord/fpphysicalinterface/__init__.py
fireREST/fmc/device/devicerecord/inlineset/__init__.py
fireREST/fmc/device/devicerecord/interfaceevent/__init__.py
fireREST/fmc/device/devicerecord/operational/__init__.py
fireREST/fmc/device/devicerecord/operational/command/__init__.py
fireREST/fmc/device/devicerecord/operational/metric/__init__.py
fireREST/fmc/device/devicerecord/physicalinterface/__init__.py
fireREST/fmc/device/devicerecord/redundantinterface/__init__.py
fireREST/fmc/device/devicerecord/routing/__init__.py
fireREST/fmc/device/devicerecord/routing/bgp/__init__.py
fireREST/fmc/device/devicerecord/routing/bgpgeneralsettings/__init__.py
fireREST/fmc/device/devicerecord/routing/ipv4staticroute/__init__.py
firerest-1.2.4.dist-info/licenses/LICENSE
firerest-1.2.4.dist-info/METADATA
firerest-1.2.4.dist-info/WHEEL
firerest-1.2.4.dist-info/top_level.txt
firerest-1.2.4.dist-info/RECORD
