Metadata-Version: 2.4
Name: fireREST
Version: 1.2.4
Summary: Python API client for Cisco Firepower Management Center (FMC)
Author-email: Oliver Kaiser <oliver.kaiser@outlook.com>
Maintainer-email: Rafal Chrabaszcz <rchrabas@cisco.com>
License: GPL-3.0-only
Project-URL: repository, https://github.com/kaisero/fireREST
Keywords: cisco,firepower,fmc,ftd,fpr,api,rest,firewall
Classifier: Development Status :: 3 - Alpha
Classifier: Intended Audience :: Developers
Classifier: Intended Audience :: Information Technology
Classifier: License :: OSI Approved :: GNU General Public License v3 or later (GPLv3+)
Classifier: Natural Language :: English
Classifier: Programming Language :: Python :: 3
Classifier: Operating System :: POSIX
Classifier: Topic :: System :: Networking :: Firewalls
Requires-Python: >=3.9
License-File: LICENSE
Requires-Dist: packaging>=20.3
Requires-Dist: requests>=2.32.4
Requires-Dist: retry>=0.9.2
Requires-Dist: simplejson>=3.17.2
Requires-Dist: urllib3>=2.6.0
Dynamic: license-file
